{
  "slug": "electricity-plugs",
  "title": { "en": "Electricity & Plugs" },
  "content": {
    "en": "France uses Type C and Type E electrical plugs and sockets, operating on 230 volts at 50 hertz. Understanding the electrical system before you travel will save you from the frustration of arriving with devices you cannot charge.\n\nThe Type E socket is the standard French socket. It has two round holes for the plug pins and a round grounding pin that protrudes from the socket itself — this is the key distinguishing feature of French sockets compared to the similar Type C. The grounding pin in the socket mates with a hole in the plug. Type C plugs (the basic two-pin European plug without grounding, also called the Europlug) fit into French Type E sockets without issues, as the grounding pin simply occupies the hole in the recess around the socket. Type F plugs (the German Schuko plug, which has grounding clips on the sides) may physically fit into some French sockets but do not make a proper ground connection, so they are not ideal.\n\nIf you are traveling from the United Kingdom, the United States, Canada, Australia, or Japan, you will need a plug adapter. Travelers from the UK (which uses Type G, the large three-rectangular-pin plug) absolutely need an adapter — UK plugs will not fit French sockets at all. American and Canadian travelers (Type A and B plugs, with flat pins) also need adapters. Australian travelers (Type I plugs, with angled flat pins) need adapters as well.\n\nThe voltage difference is an important consideration for travelers from countries using 110-120 volt systems, primarily the United States, Canada, Japan, and parts of Central and South America. Most modern electronics — laptops, smartphones, tablets, e-readers, digital cameras, and electric toothbrushes — have dual-voltage power supplies (look for 'INPUT: 100-240V' on the power adapter or charger). These devices only need a plug adapter, not a voltage converter. However, appliances with heating elements or motors — hair dryers, curling irons, flat irons, electric shavers, and some older electronics — may be single-voltage (110V only). Plugging a 110V appliance into a 230V French socket will likely destroy the appliance and could cause a fire. If you must bring such devices, you need a voltage converter (transformateur), but a better solution is to buy a dual-voltage travel version of the appliance or simply use the one provided by your hotel.\n\nMost French hotels of three stars and above provide hair dryers in the bathroom, and many also have a lower-voltage shaver socket (marked '110V shavers only') in the bathroom for charging small devices. However, these shaver sockets are low-wattage and not suitable for charging laptops or high-drain devices.\n\nPractical advice for your trip: buy a universal travel adapter before you depart — a quality one from brands like Skross, Ceptics, or EPICKA costs EUR 15-25 and works in 150+ countries, making it a worthwhile investment. Alternatively, pick up a simple French plug adapter at any airport, supermarket, or Fnac electronics store in France for EUR 5-10. If you need multiple outlets, bring a compact power strip from home with a single French adapter — this lets you charge all your devices from one adapter. USB charging has become ubiquitous; many French hotels, trains (TGV), and airports now provide USB-A and increasingly USB-C charging ports, reducing your need for adapters.\n\nPower outages are rare in France, which has one of the most reliable electrical grids in Europe, largely powered by nuclear energy. French electrical installations are generally excellent, though very old buildings (especially budget accommodations in historic centers) may have fewer outlets than you expect. Extension cords and power strips are available at any Bricomarche, Castorama, or Leroy Merlin hardware store."
  },
  "lastUpdated": "2026-03-04",
  "category": "essentials",
  "seo": {
    "metaTitle": "France Electricity & Plugs | Voltage, Adapters & Socket Guide",
    "metaDescription": "Everything you need to know about electricity in France: Type C/E plugs, 230V/50Hz, which adapters to bring, and voltage converter advice for travelers."
  }
}